SWANi_supplement/__init__.py
SWANi_supplement/icons/SWANi.icns
SWANi_supplement/icons/SWANi.png
SWANi_supplement/icons/error.svg
SWANi_supplement/icons/load.svg
SWANi_supplement/icons/ok.svg
SWANi_supplement/icons/void.svg
SWANi_supplement/icons/warn.svg
SWANi_supplement/resources/sym_brain.nii.gz
SWANi_supplement/resources/doMAP_template/binary_cerebellum.nii.gz
SWANi_supplement/resources/doMAP_template/brain_cortex_mas_OK.nii.gz
SWANi_supplement/resources/doMAP_template/brain_cortex_mas_OK.nii_2.gz
SWANi_supplement/resources/doMAP_template/mean_extension.nii.gz
SWANi_supplement/resources/doMAP_template/mean_flair.nii.gz
SWANi_supplement/resources/doMAP_template/std_final_extension.nii.gz
SWANi_supplement/resources/doMAP_template/std_final_flair.nii.gz
SWANi_supplement-0.0.5.dist-info/LICENSE
SWANi_supplement-0.0.5.dist-info/METADATA
SWANi_supplement-0.0.5.dist-info/WHEEL
SWANi_supplement-0.0.5.dist-info/top_level.txt
SWANi_supplement-0.0.5.dist-info/RECORD
