Metadata-Version: 2.1
Name: SWANi-supplement
Version: 0.0.5
Summary: Standardized Workflow for Advanced Neuroimaging - supplementary files
Author-email: Maurilio Genovese <mauriliogenovese@gmail.com>
Classifier: Programming Language :: Python :: 3
Classifier: License :: OSI Approved :: MIT License
Classifier: Operating System :: MacOS
Classifier: Operating System :: POSIX :: Linux
Requires-Python: >=3.7
License-File: LICENSE
